Metadata-Version: 2.1
Name: emBRICK
Version: 0.21
Summary: Driver to build a connection RemoteMaster <-> LWCS over Ethernet, Modbus TCP & RTU
Home-page: https://github.com/IMACS-GmbH/emBRICK/tree/main/Protocol%20Stacks/remoteBUS/Python%20via%20TCP-IP%20or%20RSxxx
Download-URL: https://github.com/IMACS-GmbH/emBRICK/raw/main/Protocol%20Stacks/remoteBUS/Python%20via%20TCP-IP%20or%20RSxxx/emBRICK-0.15.tar.gz
Author: IMACS
Author-email: serkan.sen@imacs-gmbh.de
License: MIT
Keywords: IMACS,EMBRICK,PYTHON,TCP/IP,Modbus,RTU,TCP
Classifier: Development Status :: 4 - Beta
Classifier: Intended Audience :: Developers
Classifier: Topic :: Software Development :: Build Tools
Classifier: License :: OSI Approved :: MIT License
Classifier: Programming Language :: Python :: 3
Classifier: Programming Language :: Python :: 3.8
Classifier: Programming Language :: Python :: 3.9
Classifier: Programming Language :: Python :: 3.10
Classifier: Programming Language :: Python :: 3.11
